[
  {
    "domain": "auto_save",
    "type": "fact_added",
    "key": "inyecta mas de sap_tierra, formfiller_ia, sapautomata_ia ,ia",
    "timestamp": "2026-04-05T04:56:29.084555+00:00"
  },
  {
    "domain": "auto_save",
    "type": "fact_added",
    "key": "no hay nada repetido en los kb verdad?",
    "timestamp": "2026-04-05T04:59:31.968529+00:00"
  },
  {
    "domain": "auto_save",
    "type": "fact_added",
    "key": "procede",
    "timestamp": "2026-04-05T05:00:54.978432+00:00"
  },
  {
    "domain": "auto_save",
    "type": "fact_added",
    "key": "encontraste muy poco de esto no hay mas?  Dominio\tEntradas p",
    "timestamp": "2026-04-05T05:11:52.076881+00:00"
  },
  {
    "domain": "auto_save",
    "type": "fact_added",
    "key": "realiza commit del proyecto C:\\Hooks_IA al repo git",
    "timestamp": "2026-04-05T16:48:29.006922+00:00"
  }
]