[
  {
    "domain": "auto_save",
    "type": "fact_added",
    "key": "cual seria el titulo adecuado para el documento solo escribe",
    "timestamp": "2026-04-06T17:47:54.227668+00:00"
  },
  {
    "domain": "auto_save",
    "type": "fact_added",
    "key": "lee los dos documentos con scan ocr  que estan en este path ",
    "timestamp": "2026-04-06T18:40:48.465080+00:00"
  },
  {
    "domain": "auto_save",
    "type": "fact_added",
    "key": "para hacer todo esto cuanto conocimiento tomaste del KB? del",
    "timestamp": "2026-04-06T19:44:19.421059+00:00"
  },
  {
    "domain": "auto_save",
    "type": "fact_added",
    "key": "y de este tema si existe en el internet busca",
    "timestamp": "2026-04-06T19:45:55.358856+00:00"
  },
  {
    "domain": "auto_save",
    "type": "fact_added",
    "key": "es que no fue 100% eficaz lograste colocar el indice si pero",
    "timestamp": "2026-04-06T19:50:26.078871+00:00"
  }
]